inference/__init__.py
inference/custom_interactive.py
inference/download.py
inference/engine.py
inference/flores_codes_map_indic.py
inference/indic_num_map.py
inference/normalize_punctuation.py
inference/normalize_regex_inference.py
model_configs/__init__.py
model_configs/custom_transformer.py
IndicTrans2-0.1.3.dist-info/LICENSE
IndicTrans2-0.1.3.dist-info/METADATA
IndicTrans2-0.1.3.dist-info/WHEEL
IndicTrans2-0.1.3.dist-info/entry_points.txt
IndicTrans2-0.1.3.dist-info/top_level.txt
IndicTrans2-0.1.3.dist-info/RECORD
