Metadata-Version: 2.1
Name: IndicTrans2
Version: 0.1.3
Summary: Indic NLP package
Home-page: https://github.com/AI4Bharat/IndicTrans2/
Author: AI4Bharat
Author-email: AI4Bharat@gmail.com
License: MIT
Project-URL: Documentation, https://ai4bharat.iitm.ac.in/indic-trans2/docs
Project-URL: Source, https://github.com/AI4Bharat/IndicTrans2/
Project-URL: Issues, https://github.com/AI4Bharat/IndicTrans2/issues
Classifier: Development Status :: 4 - Beta
Classifier: Intended Audience :: Developers
Classifier: Programming Language :: Python :: 3
Classifier: Programming Language :: Python :: 3.8
Classifier: Programming Language :: Python :: 3.9
Classifier: Programming Language :: Python :: 3.10
Classifier: License :: OSI Approved :: MIT License
Classifier: Operating System :: OS Independent
Requires-Python: >=3.8
License-File: LICENSE
Requires-Dist: torch >=1.6.0
Requires-Dist: fairseq >=0.10.2
Requires-Dist: transformers ==4.28.1
Requires-Dist: codecs
Requires-Dist: urduhack[tf]
Requires-Dist: nltk
Requires-Dist: sacremoses
Requires-Dist: indic-nlp-library
Requires-Dist: mosestokenizer
Requires-Dist: sacrebleu ==2.3.1
Requires-Dist: ctranslate2 ==3.9.0
Requires-Dist: gradio
Requires-Dist: sentencepiece
Requires-Dist: regex
Requires-Dist: pandas
Requires-Dist: mock
Provides-Extra: dev
Requires-Dist: pytest ; extra == 'dev'
Requires-Dist: flake8 ; extra == 'dev'
Requires-Dist: black ; extra == 'dev'
